mysqlengine/__init__.pxd
mysqlengine/__init__.py
mysqlengine/column.c
mysqlengine/column.cp313-win_amd64.pyd
mysqlengine/column.pxd
mysqlengine/column.py
mysqlengine/column.pyi
mysqlengine/constraint.c
mysqlengine/constraint.cp313-win_amd64.pyd
mysqlengine/constraint.pxd
mysqlengine/constraint.py
mysqlengine/constraint.pyi
mysqlengine/database.c
mysqlengine/database.cp313-win_amd64.pyd
mysqlengine/database.pxd
mysqlengine/database.py
mysqlengine/database.pyi
mysqlengine/dml.c
mysqlengine/dml.cp313-win_amd64.pyd
mysqlengine/dml.pxd
mysqlengine/dml.py
mysqlengine/dml.pyi
mysqlengine/element.c
mysqlengine/element.cp313-win_amd64.pyd
mysqlengine/element.pxd
mysqlengine/element.py
mysqlengine/errors.py
mysqlengine/index.c
mysqlengine/index.cp313-win_amd64.pyd
mysqlengine/index.pxd
mysqlengine/index.py
mysqlengine/index.pyi
mysqlengine/partition.c
mysqlengine/partition.cp313-win_amd64.pyd
mysqlengine/partition.pxd
mysqlengine/partition.py
mysqlengine/partition.pyi
mysqlengine/table.c
mysqlengine/table.cp313-win_amd64.pyd
mysqlengine/table.pxd
mysqlengine/table.py
mysqlengine/table.pyi
mysqlengine/utils.c
mysqlengine/utils.cp313-win_amd64.pyd
mysqlengine/utils.pxd
mysqlengine/utils.py
mysqlengine/utils.pyi
mysqlengine-1.1.5.dist-info/licenses/LICENSE
mysqlengine-1.1.5.dist-info/METADATA
mysqlengine-1.1.5.dist-info/WHEEL
mysqlengine-1.1.5.dist-info/top_level.txt
mysqlengine-1.1.5.dist-info/RECORD
