Metadata-Version: 2.4
Name: mysqlengine
Version: 1.1.5
Summary: A Cython-Accelerated, Pythonic MySQL ORM & Query Builder
Home-page: https://github.com/AresJef/MysqlEngine
Author: Jiefu Chen
Author-email: keppa1991@163.com
License: MIT license
Keywords: mysql,engine,ORM,async,cython
Classifier: Programming Language :: Python :: 3
Classifier: Operating System :: Unix
Classifier: Operating System :: MacOS :: MacOS X
Classifier: Operating System :: Microsoft :: Windows
Requires-Python: >=3.10
License-File: LICENSE
Requires-Dist: numpy>=1.25.2
Requires-Dist: pandas>=2.1.0
Requires-Dist: sqlcycli>=2.0.3
Requires-Dist: typing-extensions>=4.9.0
Dynamic: license-file
